vkdispatch_native.cp313-win_amd64.pyd
vkdispatch/__init__.py
vkdispatch/__main__.py
vkdispatch/cli.py
vkdispatch/base/buffer.py
vkdispatch/base/command_list.py
vkdispatch/base/compute_plan.py
vkdispatch/base/context.py
vkdispatch/base/descriptor_set.py
vkdispatch/base/dtype.py
vkdispatch/base/errors.py
vkdispatch/base/image.py
vkdispatch/base/init.py
vkdispatch/codegen/__init__.py
vkdispatch/codegen/abreviations.py
vkdispatch/codegen/arguments.py
vkdispatch/codegen/builder.py
vkdispatch/codegen/global_builder.py
vkdispatch/codegen/struct_builder.py
vkdispatch/execution_pipeline/buffer_builder.py
vkdispatch/execution_pipeline/command_graph.py
vkdispatch/fft/__init__.py
vkdispatch/fft/config.py
vkdispatch/fft/functions.py
vkdispatch/fft/memory_io.py
vkdispatch/fft/plan.py
vkdispatch/fft/prime_utils.py
vkdispatch/fft/resources.py
vkdispatch/fft/shader.py
vkdispatch/shader_generation/decorators.py
vkdispatch/shader_generation/mapping_shader.py
vkdispatch/shader_generation/reduction_object.py
vkdispatch/shader_generation/reduction_operations.py
vkdispatch/shader_generation/reduction_stage.py
vkdispatch/shader_generation/shader_object.py
vkdispatch/shader_generation/signature.py
vkdispatch/vkfft/__init__.py
vkdispatch/vkfft/fft_dispatcher.py
vkdispatch/vkfft/fft_plan.py
vkdispatch-0.0.30.dist-info/licenses/LICENSE
vkdispatch-0.0.30.dist-info/METADATA
vkdispatch-0.0.30.dist-info/WHEEL
vkdispatch-0.0.30.dist-info/entry_points.txt
vkdispatch-0.0.30.dist-info/top_level.txt
vkdispatch-0.0.30.dist-info/RECORD
